[
  { "name": "CHALLENGER", "short": "Chall", "min": 2000, "color": "text-sky-300", "bg": "bg-sky-300/10" },
  { "name": "GRANDMASTER", "short": "GM", "min": 1900, "color": "text-red-500", "bg": "bg-red-500/10" },
  { "name": "MASTER", "short": "Master", "min": 1850, "color": "text-purple-500", "bg": "bg-purple-500/10" },
  { "name": "DIAMOND I", "short": "Dia I", "min": 1840, "color": "text-blue-400", "bg": "bg-blue-400/10" },
  { "name": "DIAMOND II", "short": "Dia II", "min": 1825, "color": "text-blue-400", "bg": "bg-blue-400/10" },
  { "name": "DIAMOND III", "short": "Dia III", "min": 1810, "color": "text-blue-400", "bg": "bg-blue-400/10" },
  { "name": "DIAMOND IV", "short": "Dia IV", "min": 1800, "color": "text-blue-400", "bg": "bg-blue-400/10" },
  { "name": "EMERALD I", "short": "Eme I", "min": 1760, "color": "text-emerald-500", "bg": "bg-emerald-500/10" },
  { "name": "EMERALD II", "short": "Eme II", "min": 1720, "color": "text-emerald-500", "bg": "bg-emerald-500/10" },
  { "name": "EMERALD III", "short": "Eme III", "min": 1680, "color": "text-emerald-500", "bg": "bg-emerald-500/10" },
  { "name": "EMERALD IV", "short": "Eme IV", "min": 1650, "color": "text-emerald-500", "bg": "bg-emerald-500/10" },
  { "name": "PLATINUM I", "short": "Plat I", "min": 1600, "color": "text-teal-400", "bg": "bg-teal-400/10" },
  { "name": "PLATINUM II", "short": "Plat II", "min": 1560, "color": "text-teal-400", "bg": "bg-teal-400/10" },
  { "name": "PLATINUM III", "short": "Plat III", "min": 1530, "color": "text-teal-400", "bg": "bg-teal-400/10" },
  { "name": "PLATINUM IV", "short": "Plat IV", "min": 1500, "color": "text-teal-400", "bg": "bg-teal-400/10" },
  { "name": "GOLD I", "short": "Gold I", "min": 1460, "color": "text-yellow-400", "bg": "bg-yellow-400/10" },
  { "name": "GOLD II", "short": "Gold II", "min": 1420, "color": "text-yellow-400", "bg": "bg-yellow-400/10" },
  { "name": "GOLD III", "short": "Gold III", "min": 1380, "color": "text-yellow-400", "bg": "bg-yellow-400/10" },
  { "name": "GOLD IV", "short": "Gold IV", "min": 1350, "color": "text-yellow-400", "bg": "bg-yellow-400/10" },
  { "name": "SILVER I", "short": "Silver I", "min": 1310, "color": "text-slate-300", "bg": "bg-slate-300/10" },
  { "name": "SILVER II", "short": "Silver II", "min": 1270, "color": "text-slate-300", "bg": "bg-slate-300/10" },
  { "name": "SILVER III", "short": "Silver III", "min": 1230, "color": "text-slate-300", "bg": "bg-slate-300/10" },
  { "name": "SILVER IV", "short": "Silver IV", "min": 1200, "color": "text-slate-300", "bg": "bg-slate-300/10" },
  { "name": "BRONZE I", "short": "Bronze I", "min": 1160, "color": "text-amber-700", "bg": "bg-amber-700/10" },
  { "name": "BRONZE II", "short": "Bronze II", "min": 1120, "color": "text-amber-700", "bg": "bg-amber-700/10" },
  { "name": "BRONZE III", "short": "Bronze III", "min": 1080, "color": "text-amber-700", "bg": "bg-amber-700/10" },
  { "name": "BRONZE IV", "short": "Bronze IV", "min": 1050, "color": "text-amber-700", "bg": "bg-amber-700/10" },
  { "name": "IRON I", "short": "Iron I", "min": 1010, "color": "text-gray-500", "bg": "bg-gray-500/10" },
  { "name": "IRON II", "short": "Iron II", "min": 970, "color": "text-gray-500", "bg": "bg-gray-500/10" },
  { "name": "IRON III", "short": "Iron III", "min": 930, "color": "text-gray-500", "bg": "bg-gray-500/10" },
  { "name": "IRON IV", "short": "Iron IV", "min": 900, "color": "text-gray-500", "bg": "bg-gray-500/10" },
  { "name": "UNRANKED", "short": "Unrank", "min": 0, "color": "text-gray-400", "bg": "bg-gray-800" }
]
